examples/app_test/__init__.py
examples/app_test/app.py
examples/arabic/__init__.py
examples/danish/__init__.py
examples/danish/danish_zero_shot_experiment.py
examples/english/__init__.py
examples/english/english_experiment.py
examples/english/english_experiment_multiple_folds.py
examples/english/transformer_configs.py
examples/greek/__init__.py
examples/greek/greek_zero_shot_experiment.py
examples/olid/__init__.py
examples/olid/olid_zero_shot_experiment.py
mudes/__init__.py
mudes/algo/__init__.py
mudes/algo/evaluation.py
mudes/algo/language_modeling.py
mudes/algo/language_modeling_utils.py
mudes/algo/mudes_model.py
mudes/algo/predict.py
mudes/algo/preprocess.py
mudes/algo/utils.py
mudes/algo/custom_models/__init__.py
mudes/algo/custom_models/models.py
mudes/app/__init__.py
mudes/app/mudes_app.py
mudes/config/__init__.py
mudes/config/global_args.py
mudes/config/model_args.py
mudes/config/utils.py
mudes-0.4.0.dist-info/LICENSE
mudes-0.4.0.dist-info/METADATA
mudes-0.4.0.dist-info/WHEEL
mudes-0.4.0.dist-info/top_level.txt
mudes-0.4.0.dist-info/RECORD
