Metadata-Version: 2.1
Name: mudes
Version: 0.4.0
Summary: Toxic Spans Prediction
Home-page: https://github.com/TharinduDR/MUDES
Author: Tharindu Ranasinghe
Author-email: rhtdranasinghe@gmail.com
Classifier: Intended Audience :: Science/Research
Classifier: License :: OSI Approved :: Apache Software License
Classifier: Programming Language :: Python :: 3
Classifier: Topic :: Scientific/Engineering :: Artificial Intelligence
Requires-Python: >=3.6
License-File: LICENSE
Requires-Dist: numpy
Requires-Dist: requests
Requires-Dist: tqdm (>=4.47.0)
Requires-Dist: regex
Requires-Dist: transformers (>=4.2.0)
Requires-Dist: scipy
Requires-Dist: scikit-learn
Requires-Dist: tensorboardx
Requires-Dist: pandas
Requires-Dist: tokenizers
Requires-Dist: matplotlib
Requires-Dist: wandb
Requires-Dist: sentencepiece
Requires-Dist: onnxruntime
Requires-Dist: seqeval
Requires-Dist: spacy (==3.5.1)
